{
  "Ads": [
    {
      "select_main_ads": "ADMOB",
      "select_backup_ads":"APPLOVIN-D",
      "main_ads_banner": "ca-app-pub-3940256099942544/6300978111X",
      "main_ads_intertitial":"ca-app-pub-1677915521657375/1786989386",
      "native_for_admob":"ca-app-pub-1677915521657375/8160826046",
      "backup_ads_banner":"db4d5e8718b97d78",
      "backup_ads_intertitial":"518cd97722c60b52",
      "interval_intertitial": 5,
      "initialize_sdk":"107355779",
      "initialize_sdk_backup_ads":"",
      "high_paying_keyword_1": "",
      "high_paying_keyword_2": "",
      "high_paying_keyword_3": "",
      "high_paying_keyword_4": "",
      "high_paying_keyword_5": "",
      "status_app": "0",
      "link_redirect": "https://"
    }
  ],
  "More":
  [
    {
      "id":1,
      "title":"Ludo King",
      "image":"https://lh3.googleusercontent.com/GIa9Ek1a4hyqqulStVT1RC7Mus0K5nOcCaeDpt9sJEekq6lnrSIK7LDrpH0OHlFgwog=s180-rw",
      "link":"https://play.google.com/store/apps/details?id=com.ludo.king"
    },
    {
      "id":2,
      "title":"Homescapes",
      "image":"https://lh3.googleusercontent.com/-mPOu6rWotI9ZLDVnvE3ZqKdTgEfaQaqD5SArpkYwlNJM0fOhJLRfJPpPWACHLezwIQ=s180-rw",
      "link":"https://play.google.com/store/apps/details?id=com.playrix.homescapes"
    },
    {
      "id":3,
      "title":"Minecraft",
      "image":"https://lh3.googleusercontent.com/VSwHQjcAttxsLE47RuS4PqpC4LT7lCoSjE7Hx5AW_yCxtDvcnsHHvm5CTuL5BPN-uRTP=s180-rw",
      "link":"https://play.google.com/store/apps/details?id=com.mojang.minecraftpe"
    }
  ],

  "Categories": [
    {
      "id": 1,
      "name_category": "Easy",
      "image": "https://cdn1-production-images-kly.akamaized.net/8Y3LmBRFGbmO67kyYPayJbmUp_M=/640x360/smart/filters:quality(75):strip_icc():format(jpeg)/kly-media-production/medias/2514400/original/014338600_1543878323-PUBG-Mobile-update.jpg"

    },
    {
      "id": 2,
      "name_category": "Medium",
      "image": "https://img.okezone.com/content/2020/08/04/16/2256942/piala-menpora-esport-2020-tampilkan-game-mobile-legends-bang-bang-oiczwialMq.jpg"

    },
    {
      "id": 3,
      "name_category": "Hard",
      "image": "https://i1.wp.com/cdn.surgatekno.com/2019/08/spesifikasi-game-lords-mobile.jpg?resize=554%2C336&ssl=1"

    }
  ],
  "Data": [
        {
      "id": 1,
      "name_category": "Easy",
      "title": "Dengan Aplikasi GB WA",
      "image": "https://assets.jalantikus.com/assets/cache/0/0/userfiles/2020/09/11/download-aplikasi-gbwhatsapp-versi-lama-777b3.jpg",
      "description": "Cara Mengubah Tema Whtspp dengan GB WA",
      "link": "https://darwindroid.github.io/gambar/gbwhtsp.html"
    },
    {
      "id": 2,
      "name_category": "Easy",
      "title": "Dengan Aplikasi YoWhtspp",
      "image": "https://easybrazilianrecipes.com/wp-content/uploads/2020/05/YoWhatsApp.jpg",
      "description": "Cara Mengganti Tema Whtspp dgn aplikasi Yo",
      "link": "https://darwindroid.github.io/gambar/yowhtsp.html"
    },
    {
      "id": 3,
      "name_category": "Easy",
      "title": "Ganti Tema di IOS",
      "image": "https://www.tipspintar.com/wp-content/uploads/2018/11/cara-ganti-tema-whatsapp-iphone-1.jpg",
      "description": "Cara Mengganti Tema Whtspp di iOS",
      "link": "https://darwindroid.github.io/gambar/diiois.html"
    },
    {
      "id": 4,
      "name_category": "Easy",
      "title": "Ganti Tema di Android",
      "image": "https://droila.com/wp-content/uploads/2020/07/Cara-mengganti-tema-WhatsApp-YouTube.jpg",
      "description": "Cara Ganti Tema di Android",
      "link": "https://darwindroid.github.io/gambar/diandroid.html"
    }
  ]
}
